HISTORY.rst
LICENSE
MANIFEST.in
README.rst
manuscript.py
setup.py
manuscript.egg-info/PKG-INFO
manuscript.egg-info/SOURCES.txt
manuscript.egg-info/dependency_links.txt
manuscript.egg-info/entry_points.txt
manuscript.egg-info/not-zip-safe
manuscript.egg-info/requires.txt
manuscript.egg-info/top_level.txt