Metadata-Version: 1.1
Name: manuscript
Version: 0.1.0
Summary: Manuscript helps you manage your python scripts and their dependencies
Home-page: https://github.com/madjar/manuscript
Author: Georges Dubus
Author-email: georges.dubus@gmail.com
License: BSD
Keywords: manuscript
Platform: UNKNOWN
Classifier: Development Status :: 2 - Pre-Alpha
Classifier: Intended Audience :: Developers
Classifier: License :: OSI Approved :: BSD License
Classifier: Natural Language :: English
Classifier: Programming Language :: Python :: 2
Classifier: Programming Language :: Python :: 2.6
Classifier: Programming Language :: Python :: 2.7
Classifier: Programming Language :: Python :: 3
Classifier: Programming Language :: Python :: 3.3
